wmc/__init__.py
wmc/__main__.py
wmc/cli.py
wmc/dispatch.py
wmc/utils.py
wmc/commands/__init__.py
wmc/commands/record.py
wmc-0.3.3.dist-info/LICENSE
wmc-0.3.3.dist-info/METADATA
wmc-0.3.3.dist-info/WHEEL
wmc-0.3.3.dist-info/entry_points.txt
wmc-0.3.3.dist-info/top_level.txt
wmc-0.3.3.dist-info/RECORD
