Metadata-Version: 2.1
Name: wmc
Version: 0.3.3
Summary: Watch me coding, a toolbox
Home-page: https://github.com/axju/wmc
Author: axju
Author-email: axel.juraske@short-report.de
License: MIT
Platform: UNKNOWN
Classifier: Intended Audience :: Developers
Classifier: Operating System :: OS Independent
Classifier: Programming Language :: Python
Classifier: Programming Language :: Python :: 3.5
Classifier: Programming Language :: Python :: 3.6
Classifier: Programming Language :: Python :: 3.7
Classifier: Programming Language :: Python :: 3.8
Requires-Dist: ffmpeg-python
